PYUSBCAN/CANstruct.py
PYUSBCAN/ControlCAN.dll
PYUSBCAN/ControlCAN.h
PYUSBCAN/ControlCAN.lib
PYUSBCAN/ControlCAN.py
PYUSBCAN/__init__.py
PYUSBCAN-0.0.2.dist-info/METADATA
PYUSBCAN-0.0.2.dist-info/RECORD
PYUSBCAN-0.0.2.dist-info/WHEEL
PYUSBCAN-0.0.2.dist-info/top_level.txt
