Metadata-Version: 2.1
Name: PYUSBCAN
Version: 0.0.2
Summary: A Python tool to control zlg-usbcan
Home-page: https://github.com/fa1247/PYCAN
Author: XY Fan
License: UNKNOWN
Keywords: pip,USBCAN,ZLG
Platform: win
Requires-Python: >=3
